pretalx_rt/__init__.py
pretalx_rt/apps.py
pretalx_rt/exporter.py
pretalx_rt/forms.py
pretalx_rt/models.py
pretalx_rt/sync_signals.py
pretalx_rt/ui_signals.py
pretalx_rt/urls.py
pretalx_rt/views.py
pretalx_rt/locale/de_DE/LC_MESSAGES/django.po
pretalx_rt/locale/de_Formal/LC_MESSAGES/django.po
pretalx_rt/migrations/0001_initial.py
pretalx_rt/migrations/__init__.py
pretalx_rt/static/pretalx_rt/.gitkeep
pretalx_rt/templates/pretalx_rt/form.html
pretalx_rt/templates/pretalx_rt/samaware.html
pretalx_rt/templates/pretalx_rt/settings.html
pretalx_rt-2025.0.1.dist-info/licenses/LICENSE
pretalx_rt-2025.0.1.dist-info/METADATA
pretalx_rt-2025.0.1.dist-info/WHEEL
pretalx_rt-2025.0.1.dist-info/entry_points.txt
pretalx_rt-2025.0.1.dist-info/top_level.txt
pretalx_rt-2025.0.1.dist-info/RECORD
